MANIFEST.in
README.txt
__init__.py
requirements.txt
setup.py
dubbofortelnet/Dubbo.py
dubbofortelnet/__init__.py
dubbofortelnet/dubbo.py
dubbofortelnet.egg-info/PKG-INFO
dubbofortelnet.egg-info/SOURCES.txt
dubbofortelnet.egg-info/dependency_links.txt
dubbofortelnet.egg-info/top_level.txt