Metadata-Version: 1.0
Name: dubbofortelnet
Version: 1.0.4
Summary: test dubbo use telnet
Home-page: http://github.com
Author: fujun.zhang
Author-email: yirandexin@163.com
License: UNKNOWN
Platform: UNKNOWN
